{
  "/_app": "pages/_app.js",
  "/_document": "pages/_document.js",
  "/account/bookings": "pages/account/bookings.html",
  "/404": "pages/404.html",
  "/account": "pages/account.html",
  "/account/profile": "pages/account/profile.html",
  "/api/hello": "pages/api/hello.js",
  "/auth/login": "pages/auth/login.html",
  "/auth/register": "pages/auth/register.html",
  "/branches": "pages/branches.html",
  "/_error": "pages/_error.js",
  "/branches/[branchId]": "pages/branches/[branchId].js",
  "/blogs": "pages/blogs.js",
  "/": "pages/index.js",
  "/blogs/[blogId]": "pages/blogs/[blogId].js"
}